depoverflow/__init__.py
depoverflow/base.py
depoverflow/github.py
depoverflow/main.py
depoverflow/stackexchange.py
depoverflow/utils.py
depoverflow-0.1.1.dist-info/entry_points.txt
depoverflow-0.1.1.dist-info/LICENSE.txt
depoverflow-0.1.1.dist-info/WHEEL
depoverflow-0.1.1.dist-info/METADATA
depoverflow-0.1.1.dist-info/RECORD
