Metadata-Version: 2.1
Name: depoverflow
Version: 0.1.1
Summary: Watches StackOverflow answers and GitHub issues referenced in code for changes
Home-page: https://github.com/remram44/depoverflow
License: MIT
Author: Remi Rampin
Author-email: remi@rampin.org
Requires-Python: >=3.7,<4.0
Classifier: License :: OSI Approved :: MIT License
Classifier: Programming Language :: Python :: 3
Classifier: Programming Language :: Python :: 3.7
Classifier: Programming Language :: Python :: 3.8
Classifier: Programming Language :: Python :: 3.9
Requires-Dist: requests (>=2,<3)
Requires-Dist: toml (>=0.10,<0.11)
Project-URL: Repository, https://github.com/remram44/depoverflow
